{
  "source": "ocp-news",
  "name": "Open Compute Project news",
  "feed_url": "https://www.opencompute.org/projects/storage/",
  "fetched_at": "2026-06-05T03:51:51.794238+00:00",
  "next_refresh_at": "2026-06-05T04:21:51.794238+00:00",
  "entries": [],
  "errors": [
    {
      "stage": "autodiscovery",
      "message": "no alternate links found"
    },
    {
      "stage": "autodiscovery",
      "message": "no alternate links found"
    },
    {
      "stage": "autodiscovery",
      "message": "no alternate links found"
    },
    {
      "stage": "autodiscovery",
      "message": "no alternate links found"
    },
    {
      "stage": "fetch",
      "message": "all candidate URLs returned 0 entries"
    }
  ]
}
